{
    "name": "VPC Service Controls",
    "versions": {
        "attack": "10",
        "navigator": "4.2",
        "layer": "4.2"
    },
    "domain": "enterprise-attack",
    "description": "VPC Service Controls improves your ability to mitigate the risk of data exfiltration from Google Cloud services such as Cloud Storage and BigQuery. You can use VPC Service Controls to create perimeters that protect the resources and data of services that you explicitly specify.",
    "filters": {
        "platforms": [
            "Linux",
            "macOS",
            "Windows",
            "Office 365",
            "Azure AD",
            "AWS",
            "GCP",
            "Azure",
            "SaaS",
            "PRE",
            "Network"
        ]
    },
    "sorting": 0,
    "layout": {
        "layout": "side",
        "showID": false,
        "showName": true,
        "showAggregateScores": false,
        "countUnscored": false,
        "aggregateFunction": "average"
    },
    "hideDisabled": false,
    "techniques": [
        {
            "techniqueID": "T1078",
            "enabled": true,
            "showSubtechniques": false,
            "metadata": [
                {
                    "name": "category",
                    "value": "Protect"
                },
                {
                    "name": "value",
                    "value": "Significant"
                },
                {
                    "name": "comment",
                    "value": "This control is able to mitigate against abuse of compromised valid accounts by restricting access from those accounts to resources contained within the VPC perimeter the account belongs to. Resources and services contained in other VPC networks also cannot be accessed by user accounts that are not within the VPC network perimeter."
                }
            ],
            "color": "#7FFF00",
            "score_num": 100,
            "score_display": "Significant",
            "category": "Protect"
        },
        {
            "techniqueID": "T1537",
            "enabled": true,
            "showSubtechniques": false,
            "metadata": [
                {
                    "name": "category",
                    "value": "Protect"
                },
                {
                    "name": "value",
                    "value": "Significant"
                },
                {
                    "name": "comment",
                    "value": "This control may mitigate against exfiltration attempts to external cloud accounts by limiting egress of data to accounts and services contained within the VPC network perimeter. "
                }
            ],
            "color": "#7FFF00",
            "score_num": 100,
            "score_display": "Significant",
            "category": "Protect"
        },
        {
            "techniqueID": "T1530",
            "enabled": true,
            "showSubtechniques": false,
            "metadata": [
                {
                    "name": "category",
                    "value": "Protect"
                },
                {
                    "name": "value",
                    "value": "Significant"
                },
                {
                    "name": "comment",
                    "value": "This control may mitigate against access to cloud storage objects by limiting access to accounts and services contained within the VPC network perimeter that contains those cloud storage objects. "
                }
            ],
            "color": "#7FFF00",
            "score_num": 100,
            "score_display": "Significant",
            "category": "Protect"
        },
        {
            "techniqueID": "T1567",
            "enabled": true,
            "showSubtechniques": false,
            "metadata": [
                {
                    "name": "category",
                    "value": "Protect"
                },
                {
                    "name": "value",
                    "value": "Partial"
                },
                {
                    "name": "comment",
                    "value": "This control is able to mitigate against exfiltration of data over a web service. Data contained within a VPC network perimeter can not be moved to a Google cloud resource or service outside of the perimeter but may be moved to third party services or storage."
                }
            ],
            "color": "#659D32",
            "score_num": 50,
            "score_display": "Partial",
            "category": "Protect"
        },
        {
            "techniqueID": "T1619",
            "enabled": true,
            "showSubtechniques": false,
            "metadata": [
                {
                    "name": "category",
                    "value": "Protect"
                },
                {
                    "name": "value",
                    "value": "Partial"
                },
                {
                    "name": "comment",
                    "value": "This control may mitigate against discovery of cloud storage objects. This control is not able to protect metadata, such as cloud storage bucket names but can protect against discovery of the contents of a storage bucket. "
                }
            ],
            "color": "#659D32",
            "score_num": 50,
            "score_display": "Partial",
            "category": "Protect"
        }
    ],
    "gradient": {
        "colors": [
            "#ff6666",
            "#ffe766",
            "#8ec843"
        ],
        "minValue": 0,
        "maxValue": 100
    },
    "legendItems": [
        {
            "label": "Protect - Minimal",
            "color": "#9CBA7F"
        },
        {
            "label": "Protect - Partial",
            "color": "#659D32"
        },
        {
            "label": "Protect - Significant",
            "color": "#7FFF00"
        },
        {
            "label": "Detect - Minimal",
            "color": "#AEEEEE"
        },
        {
            "label": "Detect - Partial",
            "color": "#5F9F9F"
        },
        {
            "label": "Detect - Significant",
            "color": "#00FFFF"
        },
        {
            "label": "Respond - Minimal",
            "color": "#ff6b6b"
        },
        {
            "label": "Respond - Partial",
            "color": "#ff0505"
        },
        {
            "label": "Respond - Significant",
            "color": "#b80000"
        },
        {
            "label": "Mixed - Minimal",
            "color": "#bf6bff"
        },
        {
            "label": "Mixed - Partial",
            "color": "#9305ff"
        },
        {
            "label": "Mixed - Significant",
            "color": "#5c00a3"
        }
    ],
    "metadata": [],
    "showTacticRowBackground": false,
    "tacticRowBackground": "#dddddd",
    "selectTechniquesAcrossTactics": true,
    "selectSubtechniquesWithParent": false
}